Workbook
Name objetivo: Perfil!$C$10
Name prazo: Perfil!$C$8
Name tolerancia: Perfil!$C$12

Sheet Perfil
B4: INVESTIMENTO MENSAL
B5: Capital inicial (R$) | C5: 5000
B6: Aporte mensal (R$) | C6: 1000
B7: Crescimento anual do aporte (%) | C7: 0.1
B8: Prazo do investimento (anos) | C8: 5
B9: Horizonte (Meses) | C9: =prazo*12 -> 60
B10: Objetivo principal | C10: Renda
B11: Reinvestimento de rendimentos | C11: Sim
B12: Tolerância a perdas (%) | C12: 0
B13: Perfil | C13: =IF((IF(prazo<2,0,IF(prazo<=4,1,IF(prazo<=9,2,IF(prazo<=19,3,4))))+IF(tolerancia=0%,0,IF(tolerancia<=5%,1,IF(tolerancia<=15%,2,IF(tolerancia<=25%,3,4))))+IF(objetivo="Renda",0,IF(objetivo="Equilíbrio",1,2)))<=3,"Conservador",IF((IF(prazo<2,0,IF(prazo<=4,1,IF(prazo<=9,2,IF(prazo<=19,3,4))))+IF(tolerancia=0%,0,IF(tolerancia<=5%,1,IF(tolerancia<=15%,2,IF(tolerancia<=25%,3,4))))+IF(objetivo="Renda",0,IF(objetivo="Equilíbrio",1,2)))<=6,"Moderado","Agressivo")) -> Conservador
B14: Estratégia | C14: =IF(C13="Conservador","Foco em estabilidade e previsibilidade de renda",IF(C13="Moderado","Equilíbrio entre renda e crescimento","Busca maior crescimento com maior volatilidade")) -> Foco em estabilidade e previsibilidade de renda

Sheet Ativos
B3: Perfil Estratégico: | C3: =Perfil!C13 -> Conservador
B5: Classes de Ativos | C5: Descrição Conceitual | D5: Conservador | E5: Moderado | F5: Agressivo | G5: Alocação Ativa
B6: Liquidez | C6: Reserva de segurança e baixo risco. Preservação de capital. | D6: 0.6 | E6: 0.2 | F6: 0.05 | G6: =IF($C$3="Conservador",D6,IF($C$3="Moderado",E6,F6)) -> 0.6
B7: Renda Fixa Estratégica | C7: Procura superar a inflação com risco controlado. Títulos de crédito ou soberanos. | D7: 0.3 | E7: 0.4 | F7: 0.15 | G7: =IF($C$3="Conservador",D7,IF($C$3="Moderado",E7,F7)) -> 0.3
B8: Renda Variável Nacional | C8: Participação em empresas. Motor de crescimento de longo prazo, com alta volatilidade. | D8: 0.05 | E8: 0.25 | F8: 0.4 | G8: =IF($C$3="Conservador",D8,IF($C$3="Moderado",E8,F8)) -> 0.05
B9: Internacional | C9: Proteção contra risco do país e acesso a mercados globais. Hedge cambial | D9: 0.05 | E9: 0.15 | F9: 0.4 | G9: =IF($C$3="Conservador",D9,IF($C$3="Moderado",E9,F9)) -> 0.05

Sheet Simulador
B2: Cenários
B3: Base | C3: 1
B4: Otimista | C4: 1.2
B5: Estressado | C5: 0.7
B8: Cenário Selecionado | C8: Base
B10: Retorno Mensal da Carteira | C10: =SUMPRODUCT(C13:C16,E13:E16)*IF(C8="Base",1,IF(C8="Otimista",1.2,0.7)) -> 0.0084256721
B12: Classe de Ativo | C12: Alocação | D12: Retorno Anual Esperado | E12: Retorno Mensal
B13: Liquidez | C13: =Ativos!G6 -> 0.6 | D13: 0.1 | E13: =((1+D13)^(1/12))-1 -> 0.0079741404
B14: Renda Fixa Estratégica | C14: =Ativos!G7 -> 0.3 | D14: 0.115 | E14: =((1+D14)^(1/12))-1 -> 0.0091124684
B15: Renda Variável Nacional | C15: =Ativos!G8 -> 0.05 | D15: 0.15 | E15: =((1+D15)^(1/12))-1 -> 0.011714917
B16: Internacional | C16: =Ativos!G9 -> 0.05 | D16: 0.08 | E16: =((1+D16)^(1/12))-1 -> 0.0064340301
A19: Mês | B19: Saldo Inicial | C19: Aporte Mensal | D19: Base de Cálculo | E19: Retorno (%) | F19: Retorno (R$) | G19: Saldo Final
A20: {=_xlfn.SEQUENCE(Perfil!C9)} -> 1 | B20: =Perfil!C5 -> 5000 | C20: =Perfil!$C$6 -> 1000 | D20: =B20+C20 -> 6000 | E20: =$C$10 -> 0.0084256721 | F20: =D20*E20 -> 50.554033 | G20: =D20+F20 -> 6050.554
A21: 2 | B21: =IF(A21="","",G20) -> 6050.554 | C21: =IF(A21="","",IF(MOD(A21-1,12)=0,C20*(1+Perfil!$C$7),C20)) -> 1000 | D21: =IF(A21="","",B21+C21) -> 7050.554 | E21: =IF(A21="","",$C$10) -> 0.0084256721 | F21: =IF(A21="","",D21*E21) -> 59.405657 | G21: =IF(A21="","",D21+F21) -> 7109.9597
A22: 3 | B22: =IF(A22="","",G21) -> 7109.9597 | C22: =IF(A22="","",IF(MOD(A22-1,12)=0,C21*(1+Perfil!$C$7),C21)) -> 1000 | D22: =IF(A22="","",B22+C22) -> 8109.9597 | E22: =IF(A22="","",$C$10) -> 0.0084256721 | F22: =IF(A22="","",D22*E22) -> 68.331861 | G22: =IF(A22="","",D22+F22) -> 8178.2916
A23: 4 | B23: =IF(A23="","",G22) -> 8178.2916 | C23: =IF(A23="","",IF(MOD(A23-1,12)=0,C22*(1+Perfil!$C$7),C22)) -> 1000 | D23: =IF(A23="","",B23+C23) -> 9178.2916 | E23: =IF(A23="","",$C$10) -> 0.0084256721 | F23: =IF(A23="","",D23*E23) -> 77.333275 | G23: =IF(A23="","",D23+F23) -> 9255.6248
A24: 5 | B24: =IF(A24="","",G23) -> 9255.6248 | C24: =IF(A24="","",IF(MOD(A24-1,12)=0,C23*(1+Perfil!$C$7),C23)) -> 1000 | D24: =IF(A24="","",B24+C24) -> 10255.625 | E24: =IF(A24="","",$C$10) -> 0.0084256721 | F24: =IF(A24="","",D24*E24) -> 86.410532 | G24: =IF(A24="","",D24+F24) -> 10342.035
A25: 6 | B25: =IF(A25="","",G24) -> 10342.035 | C25: =IF(A25="","",IF(MOD(A25-1,12)=0,C24*(1+Perfil!$C$7),C24)) -> 1000 | D25: =IF(A25="","",B25+C25) -> 11342.035 | E25: =IF(A25="","",$C$10) -> 0.0084256721 | F25: =IF(A25="","",D25*E25) -> 95.564271 | G25: =IF(A25="","",D25+F25) -> 11437.6
A26: 7 | B26: =IF(A26="","",G25) -> 11437.6 | C26: =IF(A26="","",IF(MOD(A26-1,12)=0,C25*(1+Perfil!$C$7),C25)) -> 1000 | D26: =IF(A26="","",B26+C26) -> 12437.6 | E26: =IF(A26="","",$C$10) -> 0.0084256721 | F26: =IF(A26="","",D26*E26) -> 104.79514 | G26: =IF(A26="","",D26+F26) -> 12542.395
A27: 8 | B27: =IF(A27="","",G26) -> 12542.395 | C27: =IF(A27="","",IF(MOD(A27-1,12)=0,C26*(1+Perfil!$C$7),C26)) -> 1000 | D27: =IF(A27="","",B27+C27) -> 13542.395 | E27: =IF(A27="","",$C$10) -> 0.0084256721 | F27: =IF(A27="","",D27*E27) -> 114.10378 | G27: =IF(A27="","",D27+F27) -> 13656.499
A28: 9 | B28: =IF(A28="","",G27) -> 13656.499 | C28: =IF(A28="","",IF(MOD(A28-1,12)=0,C27*(1+Perfil!$C$7),C27)) -> 1000 | D28: =IF(A28="","",B28+C28) -> 14656.499 | E28: =IF(A28="","",$C$10) -> 0.0084256721 | F28: =IF(A28="","",D28*E28) -> 123.49085 | G28: =IF(A28="","",D28+F28) -> 14779.989
A29: 10 | B29: =IF(A29="","",G28) -> 14779.989 | C29: =IF(A29="","",IF(MOD(A29-1,12)=0,C28*(1+Perfil!$C$7),C28)) -> 1000 | D29: =IF(A29="","",B29+C29) -> 15779.989 | E29: =IF(A29="","",$C$10) -> 0.0084256721 | F29: =IF(A29="","",D29*E29) -> 132.95702 | G29: =IF(A29="","",D29+F29) -> 15912.946
A30: 11 | B30: =IF(A30="","",G29) -> 15912.946 | C30: =IF(A30="","",IF(MOD(A30-1,12)=0,C29*(1+Perfil!$C$7),C29)) -> 1000 | D30: =IF(A30="","",B30+C30) -> 16912.946 | E30: =IF(A30="","",$C$10) -> 0.0084256721 | F30: =IF(A30="","",D30*E30) -> 142.50294 | G30: =IF(A30="","",D30+F30) -> 17055.449
A31: 12 | B31: =IF(A31="","",G30) -> 17055.449 | C31: =IF(A31="","",IF(MOD(A31-1,12)=0,C30*(1+Perfil!$C$7),C30)) -> 1000 | D31: =IF(A31="","",B31+C31) -> 18055.449 | E31: =IF(A31="","",$C$10) -> 0.0084256721 | F31: =IF(A31="","",D31*E31) -> 152.1293 | G31: =IF(A31="","",D31+F31) -> 18207.579
A32: 13 | B32: =IF(A32="","",G31) -> 18207.579 | C32: =IF(A32="","",IF(MOD(A32-1,12)=0,C31*(1+Perfil!$C$7),C31)) -> 1100 | D32: =IF(A32="","",B32+C32) -> 19307.579 | E32: =IF(A32="","",$C$10) -> 0.0084256721 | F32: =IF(A32="","",D32*E32) -> 162.67933 | G32: =IF(A32="","",D32+F32) -> 19470.258
... A79: 60 | B79: =IF(A79="","",G78) -> 99769.328 | C79: =IF(A79="","",IF(MOD(A79-1,12)=0,C78*(1+Perfil!$C$7),C78)) -> 1464.1 | D79: =IF(A79="","",B79+C79) -> 101233.43 | E79: =IF(A79="","",$C$10) -> 0.0084256721 | F79: =IF(A79="","",D79*E79) -> 852.95968 | G79: =IF(A79="","",D79+F79) -> 102086.39
B80: =IF(A80="","",G79) | C80: =IF(A80="","",IF(MOD(A80-1,12)=0,C79*(1+Perfil!$C$7),C79)) | D80: =IF(A80="","",B80+C80) | E80: =IF(A80="","",$C$10) | F80: =IF(A80="","",D80*E80) | G80: =IF(A80="","",D80+F80)
B81: =IF(A81="","",G80) | C81: =IF(A81="","",IF(MOD(A81-1,12)=0,C80*(1+Perfil!$C$7),C80)) | D81: =IF(A81="","",B81+C81) | E81: =IF(A81="","",$C$10) | F81: =IF(A81="","",D81*E81) | G81: =IF(A81="","",D81+F81)
B82: =IF(A82="","",G81) | C82: =IF(A82="","",IF(MOD(A82-1,12)=0,C81*(1+Perfil!$C$7),C81)) | D82: =IF(A82="","",B82+C82) | E82: =IF(A82="","",$C$10) | F82: =IF(A82="","",D82*E82) | G82: =IF(A82="","",D82+F82)
B83: =IF(A83="","",G82) | C83: =IF(A83="","",IF(MOD(A83-1,12)=0,C82*(1+Perfil!$C$7),C82)) | D83: =IF(A83="","",B83+C83) | E83: =IF(A83="","",$C$10) | F83: =IF(A83="","",D83*E83) | G83: =IF(A83="","",D83+F83)
B84: =IF(A84="","",G83) | C84: =IF(A84="","",IF(MOD(A84-1,12)=0,C83*(1+Perfil!$C$7),C83)) | D84: =IF(A84="","",B84+C84) | E84: =IF(A84="","",$C$10) | F84: =IF(A84="","",D84*E84) | G84: =IF(A84="","",D84+F84)
B85: =IF(A85="","",G84) | C85: =IF(A85="","",IF(MOD(A85-1,12)=0,C84*(1+Perfil!$C$7),C84)) | D85: =IF(A85="","",B85+C85) | E85: =IF(A85="","",$C$10) | F85: =IF(A85="","",D85*E85) | G85: =IF(A85="","",D85+F85)
B86: =IF(A86="","",G85) | C86: =IF(A86="","",IF(MOD(A86-1,12)=0,C85*(1+Perfil!$C$7),C85)) | D86: =IF(A86="","",B86+C86) | E86: =IF(A86="","",$C$10) | F86: =IF(A86="","",D86*E86) | G86: =IF(A86="","",D86+F86)
B87: =IF(A87="","",G86) | C87: =IF(A87="","",IF(MOD(A87-1,12)=0,C86*(1+Perfil!$C$7),C86)) | D87: =IF(A87="","",B87+C87) | E87: =IF(A87="","",$C$10) | F87: =IF(A87="","",D87*E87) | G87: =IF(A87="","",D87+F87)
B88: =IF(A88="","",G87) | C88: =IF(A88="","",IF(MOD(A88-1,12)=0,C87*(1+Perfil!$C$7),C87)) | D88: =IF(A88="","",B88+C88) | E88: =IF(A88="","",$C$10) | F88: =IF(A88="","",D88*E88) | G88: =IF(A88="","",D88+F88)
B89: =IF(A89="","",G88) | C89: =IF(A89="","",IF(MOD(A89-1,12)=0,C88*(1+Perfil!$C$7),C88)) | D89: =IF(A89="","",B89+C89) | E89: =IF(A89="","",$C$10) | F89: =IF(A89="","",D89*E89) | G89: =IF(A89="","",D89+F89)
B90: =IF(A90="","",G89) | C90: =IF(A90="","",IF(MOD(A90-1,12)=0,C89*(1+Perfil!$C$7),C89)) | D90: =IF(A90="","",B90+C90) | E90: =IF(A90="","",$C$10) | F90: =IF(A90="","",D90*E90) | G90: =IF(A90="","",D90+F90)
B91: =IF(A91="","",G90) | C91: =IF(A91="","",IF(MOD(A91-1,12)=0,C90*(1+Perfil!$C$7),C90)) | D91: =IF(A91="","",B91+C91) | E91: =IF(A91="","",$C$10) | F91: =IF(A91="","",D91*E91) | G91: =IF(A91="","",D91+F91)
... B619: =IF(A619="","",G618) | C619: =IF(A619="","",IF(MOD(A619-1,12)=0,C618*(1+Perfil!$C$7),C618)) | D619: =IF(A619="","",B619+C619) | E619: =IF(A619="","",$C$10) | F619: =IF(A619="","",D619*E619) | G619: =IF(A619="","",D619+F619)

Sheet Painel
M1: =SUM(Simulador!C20:C619)+Perfil!C5 -> 78261.2
M2: =LOOKUP(9.99E+307, Simulador!G:G) -> 102086.39
M3: =M2-M1 -> 23825.188
M4: =M2*Simulador!C10 -> 860.14644
M5: =(M2/Perfil!C5)^(1/prazo)-1 -> 0.82809839
J11: ATIVO | K11: % SUGERIDO | L11: VALOR
J12: Liquidez | K12: =Ativos!G6 -> 0.6 | L12: =Perfil!$C$6*Tabela1[[#This Row],[% SUGERIDO]] -> 600
J13: Renda Fixa Estratégica | K13: =Ativos!G7 -> 0.3 | L13: =Perfil!$C$6*Tabela1[[#This Row],[% SUGERIDO]] -> 300
J14: Renda Variável Nacional | K14: =Ativos!G8 -> 0.05 | L14: =Perfil!$C$6*Tabela1[[#This Row],[% SUGERIDO]] -> 50
J15: Internacional | K15: =Ativos!G9 -> 0.05 | L15: =Perfil!$C$6*Tabela1[[#This Row],[% SUGERIDO]] -> 50
